{
  "$schema": "https://stalk-ui.com/schema/v1/registry-item.json",
  "name": "select",
  "type": "registry:ui",
  "dependencies": ["@stalk-ui/preset"],
  "registryDependencies": [],
  "files": [
    {
      "path": "src/components/ui/select.tsx",
      "type": "registry:ui",
      "content": "import * as SelectPrimitive from '@radix-ui/react-select'\nimport { forwardRef } from 'react'\nimport { cx } from 'styled-system/css'\nimport { select as selectRecipe } from 'styled-system/recipes'\n\nimport type { ComponentPropsWithoutRef, ComponentRef } from 'react'\n\nexport type SelectSize = 'sm' | 'md' | 'lg'\n\nexport const SelectRoot = SelectPrimitive.Root\nexport const SelectValue = SelectPrimitive.Value\nexport const SelectPortal = SelectPrimitive.Portal\n\nexport interface SelectTriggerProps extends ComponentPropsWithoutRef<\n  typeof SelectPrimitive.Trigger\n> {\n  invalid?: boolean\n  size?: SelectSize\n}\n\nexport type SelectProps = SelectTriggerProps\n\nexport const SelectTrigger = forwardRef<\n  ComponentRef<typeof SelectPrimitive.Trigger>,\n  SelectTriggerProps\n>(\n  (\n    { 'aria-invalid': ariaInvalid, className, disabled, invalid = false, size = 'md', ...props },\n    ref,\n  ) => {\n    const isInvalid = invalid || ariaInvalid === true || ariaInvalid === 'true'\n\n    return (\n      <SelectPrimitive.Trigger\n        ref={ref}\n        aria-invalid={isInvalid ? true : ariaInvalid}\n        className={cx(selectRecipe({ invalid: isInvalid, size }), className)}\n        data-invalid={isInvalid ? '' : undefined}\n        disabled={disabled}\n        {...props}\n      />\n    )\n  },\n)\n\nSelectTrigger.displayName = 'SelectTrigger'\n\nexport const SelectContent = forwardRef<\n  ComponentRef<typeof SelectPrimitive.Content>,\n  ComponentPropsWithoutRef<typeof SelectPrimitive.Content>\n>(({ className, ...props }, ref) => (\n  <SelectPortal>\n    <SelectPrimitive.Content\n      ref={ref}\n      className={cx('stalk-select__content', className)}\n      {...props}\n    />\n  </SelectPortal>\n))\n\nSelectContent.displayName = 'SelectContent'\n\nexport const SelectItem = forwardRef<\n  ComponentRef<typeof SelectPrimitive.Item>,\n  ComponentPropsWithoutRef<typeof SelectPrimitive.Item>\n>(({ className, children, ...props }, ref) => (\n  <SelectPrimitive.Item ref={ref} className={cx('stalk-select__item', className)} {...props}>\n    <SelectPrimitive.ItemText>{children}</SelectPrimitive.ItemText>\n  </SelectPrimitive.Item>\n))\n\nSelectItem.displayName = 'SelectItem'\n\nexport const Select = Object.assign(SelectRoot, {\n  Content: SelectContent,\n  Item: SelectItem,\n  Portal: SelectPortal,\n  Root: SelectRoot,\n  Trigger: SelectTrigger,\n  Value: SelectValue,\n})\n"
    }
  ],
  "stalk": {
    "schemaVersion": "1.0",
    "preset": {
      "semanticTokens": {},
      "recipes": ["select"]
    },
    "packageDependencies": {
      "preset": "@stalk-ui/preset"
    },
    "pandaCodegen": true,
    "importAliases": {
      "styledSystem": "styled-system"
    }
  }
}
